{
    "row1": [
      { "src": "/assets/images/1.1.png" },
      { "src": "/assets/images/1.2.png" },
      { "src": "/assets/images/1.3.png" },
      { "src": "/assets/images/1.4.png" },
      { "src": "/assets/images/1.5.png" },
      { "src": "/assets/images/1.6.png" },
      { "src": "/assets/images/1.1.png" },
      { "src": "/assets/images/1.2.png" },
      { "src": "/assets/images/1.3.png" },
      { "src": "/assets/images/1.4.png" },
      { "src": "/assets/images/1.5.png" },
      { "src": "/assets/images/1.6.png" }
    ],
    "row2": [
      { "src": "/assets/images/2.1.png" },
      { "src": "/assets/images/2.2.png" },
      { "src": "/assets/images/2.3.png" },
      { "src": "/assets/images/2.4.png" },
      { "src": "/assets/images/2.5.png" },
      { "src": "/assets/images/2.6.png" },
      { "src": "/assets/images/2.1.png" },
      { "src": "/assets/images/2.2.png" },
      { "src": "/assets/images/2.3.png" },
      { "src": "/assets/images/2.4.png" },
      { "src": "/assets/images/2.5.png" },
      { "src": "/assets/images/2.6.png" }
    ],
    "row3": [
      { "src": "/assets/images/3.1.png" },
      { "src": "/assets/images/3.2.png" },
      { "src": "/assets/images/3.3.png" },
      { "src": "/assets/images/3.4.png" },
      { "src": "/assets/images/3.5.png" },
      { "src": "/assets/images/3.6.png" },
      { "src": "/assets/images/3.1.png" },
      { "src": "/assets/images/3.2.png" },
      { "src": "/assets/images/3.3.png" },
      { "src": "/assets/images/3.4.png" },
      { "src": "/assets/images/3.5.png" },
      { "src": "/assets/images/3.6.png" }
    ],
    "row4": [
      { "src": "/assets/images/4.1.png" },
      { "src": "/assets/images/4.2.png" },
      { "src": "/assets/images/4.3.png" },
      { "src": "/assets/images/4.4.png" },
      { "src": "/assets/images/4.5.png" },
      { "src": "/assets/images/4.6.png" },
      { "src": "/assets/images/4.1.png" },
      { "src": "/assets/images/4.2.png" },
      { "src": "/assets/images/4.3.png" },
      { "src": "/assets/images/4.4.png" },
      { "src": "/assets/images/4.5.png" },
      { "src": "/assets/images/4.6.png" }
    ],
    "row5": [
      { "src": "/assets/images/5.1.png" },
      { "src": "/assets/images/5.2.png" },
      { "src": "/assets/images/5.3.png" },
      { "src": "/assets/images/5.4.png" },
      { "src": "/assets/images/5.5.png" },
      { "src": "/assets/images/5.6.png" },
      { "src": "/assets/images/5.1.png" },
      { "src": "/assets/images/5.2.png" },
      { "src": "/assets/images/5.3.png" },
      { "src": "/assets/images/5.4.png" },
      { "src": "/assets/images/5.5.png" },
      { "src": "/assets/images/5.6.png" }
    ],
    "row6": [
      { "src": "/assets/images/6.1.png" },
      { "src": "/assets/images/6.2.png" },
      { "src": "/assets/images/6.3.png" },
      { "src": "/assets/images/6.4.png" },
      { "src": "/assets/images/6.5.png" },
      { "src": "/assets/images/6.6.png" },
      { "src": "/assets/images/6.1.png" },
      { "src": "/assets/images/6.2.png" },
      { "src": "/assets/images/6.3.png" },
      { "src": "/assets/images/6.4.png" },
      { "src": "/assets/images/6.5.png" },
      { "src": "/assets/images/6.6.png" }
    ],
    "row7": [
      { "src": "/assets/images/7.1.png" },
      { "src": "/assets/images/7.2.png" },
      { "src": "/assets/images/7.3.png" },
      { "src": "/assets/images/7.4.png" },
      { "src": "/assets/images/7.5.png" },
      { "src": "/assets/images/7.6.png" },
      { "src": "/assets/images/7.1.png" },
      { "src": "/assets/images/7.2.png" },
      { "src": "/assets/images/7.3.png" },
      { "src": "/assets/images/7.4.png" },
      { "src": "/assets/images/7.5.png" },
      { "src": "/assets/images/7.6.png" }
    ],
    "row8": [
      { "src": "/assets/images/8.1.png" },
      { "src": "/assets/images/8.2.png" },
      { "src": "/assets/images/8.3.png" },
      { "src": "/assets/images/8.4.png" },
      { "src": "/assets/images/8.5.png" },
      { "src": "/assets/images/8.6.png" },
      { "src": "/assets/images/8.1.png" },
      { "src": "/assets/images/8.2.png" },
      { "src": "/assets/images/8.3.png" },
      { "src": "/assets/images/8.4.png" },
      { "src": "/assets/images/8.5.png" },
      { "src": "/assets/images/8.6.png" }
    ]
  }